flubber/__init__.py
flubber/conf/__init__.py
flubber/conf/project_template/__init__.py
flubber/conf/project_template/apps/__init__.py
flubber/conf/project_template/settings/base.yaml
flubber/conf/project_template/wsgi.py
flubber/console/__init__.py
flubber/console/application.py
flubber/console/commands/__init__.py
flubber/console/commands/startproject.py
flubber/console/commands/utils.py
flubber/console/commands/version.py
flubber/contrib/__init__.py
flubber/contrib/settings/__init__.py
flubber/contrib/settings/conf.yaml
flubber/contrib/settings/global_settings.py
flubber/contrib/utils.py
flubber/core/__init__.py
flubber/core/application.py
flubber/middleware/__init__.py
flubber/middleware/loader.py
flubber/middleware/logs.py
flubber/utils/__init__.py
flubber/utils/version.py
flubber-0.0.1a0.dist-info/entry_points.txt
flubber-0.0.1a0.dist-info/WHEEL
flubber-0.0.1a0.dist-info/METADATA
flubber-0.0.1a0.dist-info/RECORD
