Metadata-Version: 2.1
Name: flubber
Version: 0.0.1a0
Summary: 
Author: Dharwin Perez
Author-email: dhararon@hotmail.com
Requires-Python: >=3.7,<4.0
Classifier: Programming Language :: Python :: 3
Classifier: Programming Language :: Python :: 3.7
Classifier: Programming Language :: Python :: 3.8
Requires-Dist: Flask-Opentracing (>=1.1,<2.0)
Requires-Dist: cleo (>=0.7.6,<0.8.0)
Requires-Dist: factory_boy (>=2.12,<3.0)
Requires-Dist: flask (>=1.1,<2.0)
Requires-Dist: flask-sqlalchemy (>=2.4,<3.0)
Requires-Dist: flask_restful (>=0.3.7,<0.4.0)
Requires-Dist: flask_talisman (>=0.7.0,<0.8.0)
Requires-Dist: gunicorn (>=20.0,<21.0)
Requires-Dist: marshmallow-sqlalchemy (>=0.19.0,<0.20.0)
Requires-Dist: omegaconf (>=1.4,<2.0)
Requires-Dist: pre-commit (>=1.20,<2.0)
Requires-Dist: structlog (>=19.2,<20.0)
Requires-Dist: werkzeug (>=0.16.0,<0.17.0)
